{
  "bomFormat": "CycloneDX",
  "specVersion": "1.5",
  "serialNumber": "urn:uuid:cf-9297b9ba0fb427c4",
  "version": 1,
  "metadata": {
    "timestamp": "2026-03-22T15:09:56.185323+00:00",
    "tools": [
      {
        "vendor": "ClawForce",
        "name": "ClawForce Scanner",
        "version": "5.0.0"
      }
    ],
    "component": {
      "type": "application",
      "bom-ref": "pkg:clawhub/email-design",
      "name": "Email Design",
      "version": "0.1.5",
      "description": "Email marketing design with layout patterns, subject line formulas, and deliverability rules. Covers welcome sequences, promotional emails, transactional tem...",
      "purl": "pkg:generic/email-design@0.1.5",
      "licenses": [],
      "externalReferences": [
        {
          "type": "website",
          "url": "https://clawhub.ai/okaris/email-design"
        }
      ],
      "properties": [
        {
          "name": "clawforce:risk_score",
          "value": "25"
        },
        {
          "name": "clawforce:certification_tier",
          "value": "scanned"
        },
        {
          "name": "clawforce:scan_type",
          "value": "metadata"
        },
        {
          "name": "clawforce:source",
          "value": "clawhub"
        },
        {
          "name": "clawforce:scanner_version",
          "value": "5.0.0"
        },
        {
          "name": "clawforce:permission:email",
          "value": "inferred"
        }
      ]
    }
  },
  "components": [
    {
      "type": "application",
      "bom-ref": "pkg:clawhub/email-design",
      "name": "Email Design",
      "version": "0.1.5",
      "description": "Email marketing design with layout patterns, subject line formulas, and deliverability rules. Covers welcome sequences, promotional emails, transactional tem...",
      "purl": "pkg:generic/email-design@0.1.5",
      "licenses": [],
      "externalReferences": [
        {
          "type": "website",
          "url": "https://clawhub.ai/okaris/email-design"
        }
      ],
      "properties": [
        {
          "name": "clawforce:risk_score",
          "value": "25"
        },
        {
          "name": "clawforce:certification_tier",
          "value": "scanned"
        },
        {
          "name": "clawforce:scan_type",
          "value": "metadata"
        },
        {
          "name": "clawforce:source",
          "value": "clawhub"
        },
        {
          "name": "clawforce:scanner_version",
          "value": "5.0.0"
        },
        {
          "name": "clawforce:permission:email",
          "value": "inferred"
        }
      ]
    }
  ]
}