{
  "bomFormat": "CycloneDX",
  "specVersion": "1.5",
  "serialNumber": "urn:uuid:cf-fa4a656f301ce886",
  "version": 1,
  "metadata": {
    "timestamp": "2026-03-22T15:09:58.039073+00:00",
    "tools": [
      {
        "vendor": "ClawForce",
        "name": "ClawForce Scanner",
        "version": "5.0.0"
      }
    ],
    "component": {
      "type": "application",
      "bom-ref": "pkg:github/mcp-router-mcp-router",
      "name": "mcp-router",
      "version": "",
      "description": "A Unified MCP Server Management App (MCP Manager).",
      "purl": "pkg:github/mcp-router/mcp-router-mcp-router",
      "licenses": [
        {
          "license": {
            "name": "NOASSERTION"
          }
        }
      ],
      "externalReferences": [
        {
          "type": "vcs",
          "url": "https://github.com/mcp-router/mcp-router"
        },
        {
          "type": "website",
          "url": "https://github.com/mcp-router/mcp-router"
        }
      ],
      "properties": [
        {
          "name": "clawforce:risk_score",
          "value": "16"
        },
        {
          "name": "clawforce:certification_tier",
          "value": "scanned"
        },
        {
          "name": "clawforce:scan_type",
          "value": "metadata"
        },
        {
          "name": "clawforce:source",
          "value": "github"
        },
        {
          "name": "clawforce:scanner_version",
          "value": "5.0.0"
        },
        {
          "name": "clawforce:permission:execution",
          "value": "inferred"
        }
      ]
    }
  },
  "components": [
    {
      "type": "application",
      "bom-ref": "pkg:github/mcp-router-mcp-router",
      "name": "mcp-router",
      "version": "",
      "description": "A Unified MCP Server Management App (MCP Manager).",
      "purl": "pkg:github/mcp-router/mcp-router-mcp-router",
      "licenses": [
        {
          "license": {
            "name": "NOASSERTION"
          }
        }
      ],
      "externalReferences": [
        {
          "type": "vcs",
          "url": "https://github.com/mcp-router/mcp-router"
        },
        {
          "type": "website",
          "url": "https://github.com/mcp-router/mcp-router"
        }
      ],
      "properties": [
        {
          "name": "clawforce:risk_score",
          "value": "16"
        },
        {
          "name": "clawforce:certification_tier",
          "value": "scanned"
        },
        {
          "name": "clawforce:scan_type",
          "value": "metadata"
        },
        {
          "name": "clawforce:source",
          "value": "github"
        },
        {
          "name": "clawforce:scanner_version",
          "value": "5.0.0"
        },
        {
          "name": "clawforce:permission:execution",
          "value": "inferred"
        }
      ]
    }
  ]
}