{
  "bomFormat": "CycloneDX",
  "specVersion": "1.5",
  "serialNumber": "urn:uuid:cf-1f7a5b9e0421fa79",
  "version": 1,
  "metadata": {
    "timestamp": "2026-03-22T15:09:56.499536+00:00",
    "tools": [
      {
        "vendor": "ClawForce",
        "name": "ClawForce Scanner",
        "version": "5.0.0"
      }
    ],
    "component": {
      "type": "application",
      "bom-ref": "pkg:npm/shortcut-mcp",
      "name": "@shortcut/mcp",
      "version": "0.24.0",
      "description": "Shortcut MCP Server",
      "purl": "pkg:npm/shortcut-mcp@0.24.0",
      "licenses": [
        {
          "license": {
            "id": "MIT"
          }
        }
      ],
      "externalReferences": [
        {
          "type": "vcs",
          "url": "https://github.com/useshortcut/mcp-server-shortcut"
        },
        {
          "type": "website",
          "url": "https://www.npmjs.com/package/@shortcut/mcp"
        }
      ],
      "properties": [
        {
          "name": "clawforce:risk_score",
          "value": "0"
        },
        {
          "name": "clawforce:certification_tier",
          "value": "scanned"
        },
        {
          "name": "clawforce:scan_type",
          "value": "metadata"
        },
        {
          "name": "clawforce:source",
          "value": "npm"
        },
        {
          "name": "clawforce:scanner_version",
          "value": "5.0.0"
        }
      ]
    }
  },
  "components": [
    {
      "type": "application",
      "bom-ref": "pkg:npm/shortcut-mcp",
      "name": "@shortcut/mcp",
      "version": "0.24.0",
      "description": "Shortcut MCP Server",
      "purl": "pkg:npm/shortcut-mcp@0.24.0",
      "licenses": [
        {
          "license": {
            "id": "MIT"
          }
        }
      ],
      "externalReferences": [
        {
          "type": "vcs",
          "url": "https://github.com/useshortcut/mcp-server-shortcut"
        },
        {
          "type": "website",
          "url": "https://www.npmjs.com/package/@shortcut/mcp"
        }
      ],
      "properties": [
        {
          "name": "clawforce:risk_score",
          "value": "0"
        },
        {
          "name": "clawforce:certification_tier",
          "value": "scanned"
        },
        {
          "name": "clawforce:scan_type",
          "value": "metadata"
        },
        {
          "name": "clawforce:source",
          "value": "npm"
        },
        {
          "name": "clawforce:scanner_version",
          "value": "5.0.0"
        }
      ]
    }
  ]
}