{
  "bomFormat": "CycloneDX",
  "specVersion": "1.5",
  "serialNumber": "urn:uuid:cf-920aa25bda7edfc9",
  "version": 1,
  "metadata": {
    "timestamp": "2026-03-22T15:09:56.989027+00:00",
    "tools": [
      {
        "vendor": "ClawForce",
        "name": "ClawForce Scanner",
        "version": "5.0.0"
      }
    ],
    "component": {
      "type": "application",
      "bom-ref": "pkg:npm/slack-mcp-server",
      "name": "slack-mcp-server",
      "version": "1.2.3",
      "description": "Model Context Protocol (MCP) server for Slack Workspaces. This integration supports both Stdio and SSE transports, proxy settings and does not require any permissions or bots being created or approved",
      "purl": "pkg:npm/slack-mcp-server@1.2.3",
      "licenses": [
        {
          "license": {
            "id": "MIT"
          }
        }
      ],
      "externalReferences": [
        {
          "type": "vcs",
          "url": "https://github.com/korotovsky/slack-mcp-server"
        },
        {
          "type": "website",
          "url": "https://www.npmjs.com/package/slack-mcp-server"
        }
      ],
      "properties": [
        {
          "name": "clawforce:risk_score",
          "value": "6"
        },
        {
          "name": "clawforce:certification_tier",
          "value": "scanned"
        },
        {
          "name": "clawforce:scan_type",
          "value": "metadata"
        },
        {
          "name": "clawforce:source",
          "value": "npm"
        },
        {
          "name": "clawforce:scanner_version",
          "value": "5.0.0"
        },
        {
          "name": "clawforce:permission:network",
          "value": "inferred"
        },
        {
          "name": "clawforce:permission:system",
          "value": "inferred"
        }
      ]
    }
  },
  "components": [
    {
      "type": "application",
      "bom-ref": "pkg:npm/slack-mcp-server",
      "name": "slack-mcp-server",
      "version": "1.2.3",
      "description": "Model Context Protocol (MCP) server for Slack Workspaces. This integration supports both Stdio and SSE transports, proxy settings and does not require any permissions or bots being created or approved",
      "purl": "pkg:npm/slack-mcp-server@1.2.3",
      "licenses": [
        {
          "license": {
            "id": "MIT"
          }
        }
      ],
      "externalReferences": [
        {
          "type": "vcs",
          "url": "https://github.com/korotovsky/slack-mcp-server"
        },
        {
          "type": "website",
          "url": "https://www.npmjs.com/package/slack-mcp-server"
        }
      ],
      "properties": [
        {
          "name": "clawforce:risk_score",
          "value": "6"
        },
        {
          "name": "clawforce:certification_tier",
          "value": "scanned"
        },
        {
          "name": "clawforce:scan_type",
          "value": "metadata"
        },
        {
          "name": "clawforce:source",
          "value": "npm"
        },
        {
          "name": "clawforce:scanner_version",
          "value": "5.0.0"
        },
        {
          "name": "clawforce:permission:network",
          "value": "inferred"
        },
        {
          "name": "clawforce:permission:system",
          "value": "inferred"
        }
      ]
    }
  ]
}